ActiveDirectoryService/__init__.py
ActiveDirectoryService/__main__.py
ActiveDirectoryService/api.py
ActiveDirectoryService/api_test.py
ActiveDirectoryService/const.py
ActiveDirectoryService/findBy.py
ActiveDirectoryService/service.py
ActiveDirectoryService/userHomeDirectoryACLFix.py
MarkService/__init__.py
MarkService/__main__.py
MarkService/api.py
MarkService/api_test.py
MarkService/checkAndModify.py
MarkService/const.py
MarkService/createEmptyPerson.py
MarkService/markChange.py
MarkService/service.py
pih_mark-1.1.dist-info/METADATA
pih_mark-1.1.dist-info/WHEEL
pih_mark-1.1.dist-info/entry_points.txt
pih_mark-1.1.dist-info/top_level.txt
pih_mark-1.1.dist-info/RECORD
